{
  "project_info": {
    "project_number": "214528710755",
    "project_id": "firebase-baster"
  },
  "client": [
    {
      "client_info": {
        "mobilesdk_app_id": "1:214528710755:android:358a762b2a1c2fb9",
        "android_client_info": {
          "package_name": "com.team.baster"
        }
      },
      "oauth_client": [
        {
          "client_id": "214528710755-m755bsdad6ln4r435b6jgn9a6lmmjgua.apps.googleusercontent.com",
          "client_type": 1,
          "android_info": {
            "package_name": "com.team.baster",
            "certificate_hash": "5e7a302d5622bdc0f3fb0b4190bdc529c4b7ec80"
          }
        },
        {
          "client_id": "214528710755-1sjrq37odci41mssbnvandh4apqavmm5.apps.googleusercontent.com",
          "client_type": 1,
          "android_info": {
            "package_name": "com.team.baster",
            "certificate_hash": "da39a3ee5e6b4b0d3255bfef95601890afd80709"
          }
        },
        {
          "client_id": "214528710755-9uclar3nhkg4a65omtqrurglue9q2lck.apps.googleusercontent.com",
          "client_type": 3
        }
      ],
      "api_key": [
        {
          "current_key": "AIzaSyAPcdUm1ftUIavH_6UCVh6kcnQUC31A9j0"
        }
      ],
      "services": {
        "analytics_service": {
          "status": 1
        },
        "appinvite_service": {
          "status": 1,
          "other_platform_oauth_client": []
        },
        "ads_service": {
          "status": 1
        }
      }
    }
  ],
  "configuration_version": "1"
}